fairylandfuture/__init__.py
fairylandfuture/_logger.py
fairylandfuture/abstract/__init__.py
fairylandfuture/abstract/database.py
fairylandfuture/api/__init__.py
fairylandfuture/builder/__init__.py
fairylandfuture/builder/tree.py
fairylandfuture/common/__init__.py
fairylandfuture/common/file.py
fairylandfuture/common/request.py
fairylandfuture/common/validator.py
fairylandfuture/conf/__init__.py
fairylandfuture/const/__init__.py
fairylandfuture/const/database.py
fairylandfuture/const/http/__init__.py
fairylandfuture/const/http/response.py
fairylandfuture/core/__init__.py
fairylandfuture/core/metaclass/__init__.py
fairylandfuture/core/metaclass/singleton.py
fairylandfuture/core/superclass/__init__.py
fairylandfuture/core/superclass/decorators.py
fairylandfuture/core/superclass/enumerate.py
fairylandfuture/core/superclass/exception.py
fairylandfuture/core/superclass/fakerlib.py
fairylandfuture/core/superclass/file.py
fairylandfuture/core/superclass/schema.py
fairylandfuture/core/superclass/structure.py
fairylandfuture/core/superclass/validators.py
fairylandfuture/database/__init__.py
fairylandfuture/database/__postgresql.py
fairylandfuture/database/elasticsearch.py
fairylandfuture/database/mysql.py
fairylandfuture/database/postgresql.py
fairylandfuture/decorators/__init__.py
fairylandfuture/decorators/generics.py
fairylandfuture/decorators/methods.py
fairylandfuture/enums/__init__.py
fairylandfuture/enums/_datetime.py
fairylandfuture/enums/_encode.py
fairylandfuture/enums/_file.py
fairylandfuture/enums/http/__init__.py
fairylandfuture/enums/http/_request.py
fairylandfuture/exceptions/__init__.py
fairylandfuture/exceptions/database.py
fairylandfuture/exceptions/elasticsearch.py
fairylandfuture/exceptions/file.py
fairylandfuture/exceptions/generic.py
fairylandfuture/exceptions/messages/__init__.py
fairylandfuture/exceptions/messages/database.py
fairylandfuture/exceptions/messages/elasticsearch.py
fairylandfuture/helpers/__init__.py
pypi_fairylandfuture-1.3.3.dist-info/licenses/LICENSE
pypi_fairylandfuture-1.3.3.dist-info/METADATA
pypi_fairylandfuture-1.3.3.dist-info/WHEEL
pypi_fairylandfuture-1.3.3.dist-info/top_level.txt
pypi_fairylandfuture-1.3.3.dist-info/RECORD
