Metadata-Version: 2.4
Name: pypi-fairylandfuture
Version: 1.3.3
Summary: A comprehensive Python package for FairylandFuture project
Author-email: FairylandTech <fairylandfuture@protonmail.com>
License:                     GNU AFFERO GENERAL PUBLIC LICENSE
Project-URL: Homepage, https://github.com/FairylandTech/pypi-fairylandfuture
Project-URL: Repository, https://github.com/FairylandTech/pypi-fairylandfuture
Project-URL: Documentation, https://github.com/FairylandTech/pypi-fairylandfuture#readme
Project-URL: Issues, https://github.com/FairylandTech/pypi-fairylandfuture/issues
Keywords: fairylandfuture,fairyland,toolkit
Classifier: Development Status :: 4 - Beta
Classifier: Intended Audience :: Developers
Classifier: License :: OSI Approved :: GNU General Public License v3 (GPLv3)
Classifier: Programming Language :: Python :: 3
Classifier: Programming Language :: Python :: 3.12
Classifier: Framework :: Django
Requires-Python: >=3.12
License-File: LICENSE
Requires-Dist: pypi-fairylandlogger
Requires-Dist: loguru
Requires-Dist: python-dateutil
Requires-Dist: python-dotenv
Requires-Dist: requests
Requires-Dist: pyyaml
Requires-Dist: cryptography
Requires-Dist: netifaces
Requires-Dist: pydantic
Requires-Dist: ua-parser
Requires-Dist: user-agents
Requires-Dist: pymysql
Requires-Dist: psycopg2-binary
Requires-Dist: mysql-connector-python
Requires-Dist: sqlalchemy
Requires-Dist: DBUtils
Requires-Dist: aiomysql
Requires-Dist: psycopg[async,binary]
Requires-Dist: kafka-python
Requires-Dist: elasticsearch[async]
Requires-Dist: opensearch-py
Requires-Dist: faker
Requires-Dist: pypinyin
Requires-Dist: django
Requires-Dist: djangorestframework
Requires-Dist: django-redis
Requires-Dist: django-filter
Requires-Dist: django-cors-headers
Requires-Dist: django-simpleui
Requires-Dist: django-tenant-schemas
Requires-Dist: django-tenants
Requires-Dist: django-extensions
Requires-Dist: django-celery-results
Requires-Dist: drf-yasg
Requires-Dist: drf-spectacular
Requires-Dist: coreapi
Requires-Dist: pygments
Requires-Dist: markdown
Requires-Dist: uritemplate
Requires-Dist: selenium
Requires-Dist: webdriver-manager
Requires-Dist: beautifulsoup4
Requires-Dist: types-requests
Requires-Dist: types-python-dateutil
Requires-Dist: types-PyYAML
Requires-Dist: django-stubs
Requires-Dist: django-stubs-ext
Requires-Dist: djangorestframework-stubs
Requires-Dist: types-cryptography
Requires-Dist: pandas-stubs
Requires-Dist: pip-tools
Requires-Dist: pipreqs
Requires-Dist: pipdeptree
Requires-Dist: pip-review
Requires-Dist: pip-autoremove
Requires-Dist: pigar
Requires-Dist: setuptools
Requires-Dist: wheel
Requires-Dist: pip
Requires-Dist: black
Requires-Dist: flake8
Requires-Dist: isort
Requires-Dist: mypy
Requires-Dist: pydocstyle
Requires-Dist: pylint
Requires-Dist: autopep8
Requires-Dist: pytest
Requires-Dist: pytest-django
Requires-Dist: pytest-cov
Requires-Dist: ruff
Requires-Dist: pyright
Requires-Dist: importlab
Dynamic: license-file
